LICENSE
README.md
setup.py
subprober/__init__.py
subprober/subprober.py
subprober.egg-info/PKG-INFO
subprober.egg-info/SOURCES.txt
subprober.egg-info/dependency_links.txt
subprober.egg-info/entry_points.txt
subprober.egg-info/requires.txt
subprober.egg-info/top_level.txt
subprober/modules/__init__.py
subprober/modules/handler.py
subprober/modules/banner/__init__.py
subprober/modules/banner/banner.py
subprober/modules/cli/__init__.py
subprober/modules/cli/cli.py
subprober/modules/config/__init__.py
subprober/modules/config/config.py
subprober/modules/core/__init__.py
subprober/modules/core/core.py
subprober/modules/dns/__init__.py
subprober/modules/dns/dns.py
subprober/modules/extender/__init__.py
subprober/modules/extender/extender.py
subprober/modules/filters/__init__.py
subprober/modules/filters/filters.py
subprober/modules/hash/__init__.py
subprober/modules/hash/hash.py
subprober/modules/help/__init__.py
subprober/modules/help/help.py
subprober/modules/jarmhash/__init__.py
subprober/modules/jarmhash/jarmhash.py
subprober/modules/logger/__init__.py
subprober/modules/logger/logger.py
subprober/modules/matchers/__init__.py
subprober/modules/matchers/matchers.py
subprober/modules/save/__init__.py
subprober/modules/save/save.py
subprober/modules/screenshot/__init__.py
subprober/modules/screenshot/screenshot.py
subprober/modules/tls/__init__.py
subprober/modules/tls/tls.py
subprober/modules/update/__init__.py
subprober/modules/update/update.py
subprober/modules/utils/__init__.py
subprober/modules/utils/utils.py
subprober/modules/validate/__init__.py
subprober/modules/validate/headless.py
subprober/modules/version/__init__.py
subprober/modules/version/version.py
subprober/modules/websocket/__init__.py
subprober/modules/websocket/websocket.py