Metadata-Version: 2.1
Name: subprober
Version: 3.0.1
Summary: Subprober - An essential HTTP multi-purpose Probing Tool for Penetration Testers and Security Researchers with Asynchronous httpx client support
Home-page: https://github.com/RevoltSecurities/Subprober
Author: D. Sanjai Kumar
Author-email: bughunterz0047@gmail.com
License-File: LICENSE
Requires-Dist: aiodns>=3.2.0
Requires-Dist: aiofiles>=24.1.0
Requires-Dist: aiojarm>=0.2.2
Requires-Dist: alive_progress>=3.2.0
Requires-Dist: appdirs>=1.4.4
Requires-Dist: art>=6.4
Requires-Dist: asynciolimiter>=1.1.1
Requires-Dist: beautifulsoup4>=4.12.3
Requires-Dist: bs4>=0.0.2
Requires-Dist: lxml>=5.3.0
Requires-Dist: colorama>=0.4.6
Requires-Dist: cryptography>=44.0.0
Requires-Dist: fake_useragent>=1.5.1
Requires-Dist: httpx>=0.28.1
Requires-Dist: mmh3>=5.0.1
Requires-Dist: playwright>=1.49.1
Requires-Dist: Requests>=2.32.3
Requires-Dist: rich>=13.9.4
Requires-Dist: setuptools>=75.2.0
Requires-Dist: simhash>=2.1.2
Requires-Dist: urllib3>=1.26.18
Requires-Dist: uvloop>=0.21.0
Requires-Dist: websockets>=14.1
